sandpiper/__init__.py
sandpiper/concurrency.py
sandpiper/mixin.py
sandpiper/storage.py
sandpiper/util.py
sandpiper/adapter/__init__.py
sandpiper/adapter/abstract.py
sandpiper/adapter/dynamodb.py
sandpiper/adapter/inmemory.py
sandpiper/adapter/memcached.py
sandpiper/adapter/xredis.py
sandpiper-0.12.1.dist-info/DESCRIPTION.rst
sandpiper-0.12.1.dist-info/METADATA
sandpiper-0.12.1.dist-info/RECORD
sandpiper-0.12.1.dist-info/WHEEL
sandpiper-0.12.1.dist-info/metadata.json
sandpiper-0.12.1.dist-info/top_level.txt
