Metadata-Version: 2.0
Name: sandpiper
Version: 0.12.1
Summary: A Generic/Extendible Key-value Store Interface Library
Home-page: https://github.com/shiroyuki/sandpiper
Author: Juti Noppornpitak
Author-email: juti_n@yahoo.co.jp
License: MIT
Platform: UNKNOWN
Classifier: Development Status :: 5 - Production/Stable
Classifier: Intended Audience :: Developers
Classifier: License :: OSI Approved :: MIT License
Classifier: Operating System :: OS Independent
Classifier: Programming Language :: Python
Classifier: Programming Language :: Python :: 3
Classifier: Topic :: Software Development :: Libraries
